count_ones.v
module fulladder(
    input a, b, cin, 
    output sum, cout
);
    assign sum = a^b^cin;
    assign cout = a&b|b&cin|cin&a;
endmodule

module ripple_adder(
    input wire [3:0]a, 
    input wire [3:0]b, 
    input wire cin, 
    output wire [3:0]s, 
    output wire cout
);
    wire [2:0]c;
    fulladder f1(a[0],b[0],cin,s[0],c[0]);
    fulladder f2(a[1],b[1],c[0],s[1],c[1]);
    fulladder f3(a[2],b[2],c[1],s[2],c[2]);
    fulladder f4(a[3],b[3],c[2],s[3],cout);
endmodule

module count_ones(
    input [7:0] binary_in,
    output [3:0] ones_count
);
    // Split the input into two 4-bit groups
    wire [3:0] lower_bits = {3'b000, binary_in[0]} + 
                           {3'b000, binary_in[1]} + 
                           {3'b000, binary_in[2]} +
                           {3'b000, binary_in[3]};
                           
    wire [3:0] upper_bits = {3'b000, binary_in[4]} + 
                           {3'b000, binary_in[5]} + 
                           {3'b000, binary_in[6]} +
                           {3'b000, binary_in[7]};
    
    // Use ripple adder to sum the two groups
    wire cout;
    ripple_adder ra(
        .a(lower_bits),
        .b(upper_bits),
        .cin(1'b0),
        .s(ones_count),
        .cout(cout)
    );

endmodule

ones_tb.v
`timescale 1ns/1ps

module count_ones_tb;
    reg [7:0] binary_in;
    wire [3:0] ones_count;

    // Instantiate the count_ones module
    count_ones uut (
        .binary_in(binary_in),
        .ones_count(ones_count)
    );

    initial begin
        // Initialize the dump file for GTKWave
        $dumpfile("count_ones_tb.vcd");
        $dumpvars(0, count_ones_tb);

        // Monitor the inputs and outputs
        $monitor("Input: %b, Number of 1s: %d", binary_in, ones_count);

        // Test cases with expected outputs
        binary_in = 8'b00000000; #10; // Expected output: 0
        binary_in = 8'b11111111; #10; // Expected output: 8
        binary_in = 8'b10101010; #10; // Expected output: 4
        binary_in = 8'b11001100; #10; // Expected output: 4
        binary_in = 8'b11100110; #10; // Expected output: 5
        binary_in = 8'b10000001; #10; // Expected output: 2
        binary_in = 8'b00100110; #10; // Expected output: 4
        binary_in = 8'b00001111; #10; // Expected output: 4
        binary_in = 8'b01010101; #10; // Expected output: 4

        // Finish simulation
        $finish;
    end
endmodule

count_ones_tb.vcd
$date
	Tue Nov 05 15:20:02 2024
$end
$version
	Icarus Verilog
$end
$timescale
	1ps
$end
$scope module count_ones_tb $end
$var wire 4 ! ones_count [3:0] $end
$var reg 8 " binary_in [7:0] $end
$scope module uut $end
$var wire 8 # binary_in [7:0] $end
$var wire 4 $ upper_bits [3:0] $end
$var wire 4 % ones_count [3:0] $end
$var wire 4 & lower_bits [3:0] $end
$var wire 1 ' cout $end
$scope module ra $end
$var wire 4 ( a [3:0] $end
$var wire 4 ) b [3:0] $end
$var wire 1 * cin $end
$var wire 4 + s [3:0] $end
$var wire 1 ' cout $end
$var wire 3 , c [2:0] $end
$scope module f1 $end
$var wire 1 - a $end
$var wire 1 . b $end
$var wire 1 * cin $end
$var wire 1 / cout $end
$var wire 1 0 sum $end
$upscope $end
$scope module f2 $end
$var wire 1 1 a $end
$var wire 1 2 b $end
$var wire 1 3 cin $end
$var wire 1 4 cout $end
$var wire 1 5 sum $end
$upscope $end
$scope module f3 $end
$var wire 1 6 a $end
$var wire 1 7 b $end
$var wire 1 8 cin $end
$var wire 1 9 cout $end
$var wire 1 : sum $end
$upscope $end
$scope module f4 $end
$var wire 1 ; a $end
$var wire 1 < b $end
$var wire 1 = cin $end
$var wire 1 ' cout $end
$var wire 1 > sum $end
$upscope $end
$upscope $end
$upscope $end
$upscope $end
$enddefinitions $end
$comment Show the parameter values. $end
$dumpall
$end
#0
$dumpvars
0>
0=
0<
0;
0:
09
08
07
06
05
04
03
02
01
00
0/
0.
0-
b0 ,
b0 +
0*
b0 )
b0 (
0'
b0 &
b0 %
b0 $
b0 #
b0 "
b0 !
$end
#10000
b1000 !
b1000 %
b1000 +
1>
1=
b100 ,
19
16
17
b100 &
b100 (
b100 $
b100 )
b11111111 "
b11111111 #
#20000
1:
b100 !
b100 %
b100 +
0>
18
0=
14
b10 ,
09
11
06
12
07
b10 &
b10 (
b10 $
b10 )
b10101010 "
b10101010 #
#30000
b10 &
b10 (
b10 $
b10 )
b11001100 "
b11001100 #
#40000
b101 !
b101 %
b101 +
10
1.
b10 &
b10 (
b11 $
b11 )
b11100110 "
b11100110 #
#50000
15
0:
13
08
1/
b1 ,
04
b10 !
b10 %
b10 +
00
1-
01
02
b1 &
b1 (
b1 $
b1 )
b10000001 "
b10000001 #
#60000
03
0:
0/
08
10
b11 !
b11 %
b11 +
15
b0 ,
04
0-
11
b10 &
b10 (
b1 $
b1 )
b100110 "
b100110 #
#70000
05
1:
b100 !
b100 %
b100 +
00
01
16
0.
b100 &
b100 (
b0 $
b0 )
b1111 "
b1111 #
#80000
18
b10 ,
14
b100 !
b100 %
b100 +
1:
11
06
12
b10 &
b10 (
b10 $
b10 )
b1010101 "
b1010101 #
